{"_id":{"$oid":"5e6d3e29d15d2c2ec652e597"},"text":"More #SpecialEducation guidance on the school closures from @OHEducation https://t.co/zv0qYY0QXJ… https://t.co/hUEFS0L6MG","id":{"$numberLong":"1238923909069709312"},"date":{"$date":{"$numberLong":"1584217452000"}},"username":"Laura_G_Anthony"}
{"_id":{"$oid":"5e6d3e29d15d2c2ec652e598"},"text":"RT @mkvenu1: Watch | 'We Will Approach SC If Centre Denies GST Compensation': Kerala's FM https://t.co/UJ8olfbrKH via @thewire_in?lang=en","id":{"$numberLong":"1238922224033083392"},"date":{"$date":{"$numberLong":"1584217050000"}},"username":"kamarajdisciple"}
{"_id":{"$oid":"5e6d3e29d15d2c2ec652e599"},"text":"Newly-issued guidance from ODE on the Coronavirus school closures https://t.co/yZT1ypinSK","id":{"$numberLong":"1238920763815665670"},"date":{"$date":{"$numberLong":"1584216702000"}},"username":"djlamps"}
{"_id":{"$oid":"5e6d3e29d15d2c2ec652e59a"},"text":"RT @SErfullt: The article from @SexworkID about what sex workers and their clients should know regarding the spread of coronavirus is also…","id":{"$numberLong":"1238919600860884992"},"date":{"$date":{"$numberLong":"1584216425000"}},"username":"barbbrents"}
{"_id":{"$oid":"5e6d3e29d15d2c2ec652e59b"},"text":".@VladaMK sets up crisis management body after 6 new #coronavirus cases confirmed: Minister @VFilipche \nhttps://t.co/iHS7B8UEDK","id":{"$numberLong":"1238916882276679680"},"date":{"$date":{"$numberLong":"1584215777000"}},"username":"MIA_NEWS_en"}
{"_id":{"$oid":"5e6d3e29d15d2c2ec652e59c"},"text":"@astrograph Hi, Derrick. Our flights to and from India are in service. For important travel updates, please visit… https://t.co/Wq32yfXCzS","id":{"$numberLong":"1238916331048701965"},"date":{"$date":{"$numberLong":"1584215645000"}},"username":"qrsupport"}
{"_id":{"$oid":"5e6d3e29d15d2c2ec652e59d"},"text":"The effect of underfunding the health sector &amp; provision of social services globally has greatly affected the respo… https://t.co/SVvjY2WchB","id":{"$numberLong":"1238914399403991040"},"date":{"$date":{"$numberLong":"1584215185000"}},"username":"mwachondahuey"}
{"_id":{"$oid":"5e6d3e29d15d2c2ec652e59e"},"text":"RT @mkvenu1: Watch | 'We Will Approach SC If Centre Denies GST Compensation': Kerala's FM https://t.co/UJ8olfbrKH via @thewire_in?lang=en","id":{"$numberLong":"1238913050364665858"},"date":{"$date":{"$numberLong":"1584214863000"}},"username":"indna14278"}
{"_id":{"$oid":"5e6d3e29d15d2c2ec652e59f"},"text":"[Italian Red Cross Launches Bitcoin Fundraiser To Combat Coronavirus]\n\nAccording to Cointelegraph, t...… https://t.co/PtWqBS7xLG","id":{"$numberLong":"1238911791058411520"},"date":{"$date":{"$numberLong":"1584214563000"}},"username":"shochibkhan"}
{"_id":{"$oid":"5e6d3e29d15d2c2ec652e5a0"},"text":"RT @mkvenu1: Watch | 'We Will Approach SC If Centre Denies GST Compensation': Kerala's FM https://t.co/UJ8olfbrKH via @thewire_in?lang=en","id":{"$numberLong":"1238911021391233026"},"date":{"$date":{"$numberLong":"1584214380000"}},"username":"parwez1"}
{"_id":{"$oid":"5e6d3e29d15d2c2ec652e5a1"},"text":"RT @mkvenu1: Watch | 'We Will Approach SC If Centre Denies GST Compensation': Kerala's FM https://t.co/UJ8olfbrKH via @thewire_in?lang=en","id":{"$numberLong":"1238909135116292103"},"date":{"$date":{"$numberLong":"1584213930000"}},"username":"doc_shak"}
{"_id":{"$oid":"5e6d3e29d15d2c2ec652e5a2"},"text":"RT @mkvenu1: Watch | 'We Will Approach SC If Centre Denies GST Compensation': Kerala's FM https://t.co/UJ8olfbrKH via @thewire_in?lang=en","id":{"$numberLong":"1238904870985334784"},"date":{"$date":{"$numberLong":"1584212913000"}},"username":"Natalia45778542"}
{"_id":{"$oid":"5e6d3e29d15d2c2ec652e5a3"},"text":"RT @mkvenu1: Watch | 'We Will Approach SC If Centre Denies GST Compensation': Kerala's FM https://t.co/UJ8olfbrKH via @thewire_in?lang=en","id":{"$numberLong":"1238900100857909248"},"date":{"$date":{"$numberLong":"1584211776000"}},"username":"dmurugeshan2"}
{"_id":{"$oid":"5e6d3e29d15d2c2ec652e5a4"},"text":"RT @UU_University: Björn Olsen, professor of infectious medicine at Uppsala University, on the coronavirus: “We need smart strategies” http…","id":{"$numberLong":"1238897533646241797"},"date":{"$date":{"$numberLong":"1584211164000"}},"username":"shaima2030"}
{"_id":{"$oid":"5e6d3e29d15d2c2ec652e5a5"},"text":"RT @mkvenu1: Watch | 'We Will Approach SC If Centre Denies GST Compensation': Kerala's FM https://t.co/UJ8olfbrKH via @thewire_in?lang=en","id":{"$numberLong":"1238892418445070338"},"date":{"$date":{"$numberLong":"1584209944000"}},"username":"praveenasharma3"}
{"_id":{"$oid":"5e6d3e2ad15d2c2ec652e5a6"},"text":"RT @traceyecorder: 40 Republicans voted against #HR6201 the #FamiliesFirstBill \n\nWe should all remember their names and that they chose gre…","id":{"$numberLong":"1238924699159212034"},"date":{"$date":{"$numberLong":"1584217641000"}},"username":"JeanMil45726010"}
{"_id":{"$oid":"5e6d3e2ad15d2c2ec652e5a7"},"text":"RT @WhoIsClayJames: More than 1/2 of the #coronavirus patients globally have recovered. Let’s spread the good information as well. https://…","id":{"$numberLong":"1238924699238830082"},"date":{"$date":{"$numberLong":"1584217641000"}},"username":"Aye_Lyssah"}
{"_id":{"$oid":"5e6d3e2ad15d2c2ec652e5a8"},"text":"RT @GabrielScally: English #publichealth leader Prof John Ashton has had his @Twitter account disabled this evening. He criticised the UK G…","id":{"$numberLong":"1238924699335381001"},"date":{"$date":{"$numberLong":"1584217641000"}},"username":"ForFreeSpeech1"}
{"_id":{"$oid":"5e6d3e2ad15d2c2ec652e5a9"},"text":"RT @AndyOstroy: Dear @Surgeon_General @JeromeAdamsMD: you don’t want the press criticizing @realDonaldTrump’s and the administration’s mish…","id":{"$numberLong":"1238924699540873216"},"date":{"$date":{"$numberLong":"1584217641000"}},"username":"AlexKahill"}
{"_id":{"$oid":"5e6d3e2ad15d2c2ec652e5aa"},"text":"RT @trueDennisNedry: @nationalpost Here is the data on Canada's ICU beds - one of the lowest in the modern world. Yet Hajdu/Mr.T says they…","id":{"$numberLong":"1238924699792478208"},"date":{"$date":{"$numberLong":"1584217641000"}},"username":"OnlyJackTripper"}
{"_id":{"$oid":"5e6d3e2ad15d2c2ec652e5ab"},"text":"RT @djdommb: Spread the good details just like you spread the negative ones","id":{"$numberLong":"1238924700224327680"},"date":{"$date":{"$numberLong":"1584217641000"}},"username":"laker5523"}
{"_id":{"$oid":"5e6d3e2ad15d2c2ec652e5ac"},"text":"RT @tommyNtour: I found the supermarket trip today quite upsetting. \n\nSome with trolleys overloaded \n\nAnd most ( mostly elderly )  unable t…","id":{"$numberLong":"1238924700295802881"},"date":{"$date":{"$numberLong":"1584217641000"}},"username":"thehippyhen"}
{"_id":{"$oid":"5e6d3e2ad15d2c2ec652e5ad"},"text":"RT @DrDenaGrayson: No surprise, @Jim_Jordan voted “NO” on the #Coronavirus Response Bill.\n\nFellow Americans, remember the names of Jim Jord…","id":{"$numberLong":"1238924700237082629"},"date":{"$date":{"$numberLong":"1584217641000"}},"username":"meo_ryan"}
{"_id":{"$oid":"5e6d3e2bd15d2c2ec652e5ae"},"text":"RT @djdommb: Spread the good details just like you spread the negative ones","id":{"$numberLong":"1238924700509757440"},"date":{"$date":{"$numberLong":"1584217641000"}},"username":"princessbatesss"}
{"_id":{"$oid":"5e6d3e2bd15d2c2ec652e5af"},"text":"As you all have heard Bergamo is currently the most hit town in Italy by the spread of #coronavirus and bed places… https://t.co/9eQUKIQRMV","id":{"$numberLong":"1238924701361111042"},"date":{"$date":{"$numberLong":"1584217641000"}},"username":"ilariavitali85"}
{"_id":{"$oid":"5e6d3e2bd15d2c2ec652e5b0"},"text":"Keep seeing images like this from places like Chicago and NYC in my feed. This combines the stupidity of the toilet… https://t.co/wrl1j5FSTg","id":{"$numberLong":"1238924701336043521"},"date":{"$date":{"$numberLong":"1584217641000"}},"username":"lancesalyers"}
{"_id":{"$oid":"5e6d3e2bd15d2c2ec652e5b1"},"text":"RT @WarsontheBrink: Tehran, Iran was extremely crowded today despite the fact that the #Coronavirus outbreak in the country is extremely ba…","id":{"$numberLong":"1238924701650444289"},"date":{"$date":{"$numberLong":"1584217641000"}},"username":"makGauBalak"}
{"_id":{"$oid":"5e6d3e2bd15d2c2ec652e5b2"},"text":"RT @thacondition: This is HARD AS FUCK.","id":{"$numberLong":"1238924701696753665"},"date":{"$date":{"$numberLong":"1584217641000"}},"username":"YoGirlMarly"}
{"_id":{"$oid":"5e6d3e2bd15d2c2ec652e5b3"},"text":"RT @ccarolinekruer: Remember this when someone says “this shouldn’t be political.” \n\nThen tell me why 40 Republicans just voted against sav…","id":{"$numberLong":"1238924701948354562"},"date":{"$date":{"$numberLong":"1584217641000"}},"username":"A_Macura"}
{"_id":{"$oid":"5e6d3e2bd15d2c2ec652e5b4"},"text":"Yes people! Stop it. Makes no sense.","id":{"$numberLong":"1238924701847732230"},"date":{"$date":{"$numberLong":"1584217641000"}},"username":"FitNHappyDiva"}
{"_id":{"$oid":"5e6d3e2bd15d2c2ec652e5b5"},"text":"RT @PHE_uk: We’ve updated our #Coronavirus (#COVID19) data dashboard, including new cases and cases by upper tier local authority. The link…","id":{"$numberLong":"1238924702049067008"},"date":{"$date":{"$numberLong":"1584217641000"}},"username":"Alone2Alone"}
{"_id":{"$oid":"5e6d3e2bd15d2c2ec652e5b6"},"text":"RT @Chandersaur: Someone start writing the script, this bout to win an Oscar.","id":{"$numberLong":"1238924702158131200"},"date":{"$date":{"$numberLong":"1584217641000"}},"username":"t_hall0770"}
{"_id":{"$oid":"5e6d3e2bd15d2c2ec652e5b7"},"text":"RT @djdommb: Spread the good details just like you spread the negative ones","id":{"$numberLong":"1238924702229331970"},"date":{"$date":{"$numberLong":"1584217641000"}},"username":"b3lkinn"}
{"_id":{"$oid":"5e6d3e2bd15d2c2ec652e5b8"},"text":"RT @petravdhulst: Those who continuously are fearful of something, feel fearful of something and act fearful upon something, are likely to…","id":{"$numberLong":"1238924702405533701"},"date":{"$date":{"$numberLong":"1584217641000"}},"username":"petravdhulst"}
{"_id":{"$oid":"5e6d3e2bd15d2c2ec652e5b9"},"text":"RT @AndyOstroy: Dear @Surgeon_General @JeromeAdamsMD: you don’t want the press criticizing @realDonaldTrump’s and the administration’s mish…","id":{"$numberLong":"1238924702640410625"},"date":{"$date":{"$numberLong":"1584217641000"}},"username":"Meemaw570"}
{"_id":{"$oid":"5e6d3e2bd15d2c2ec652e5ba"},"text":"RT @joncoopertweets: Isn’t it ironic that two of the #coronavirus hotspots are the the Trump White House and Mar-a-Lago? 🦠","id":{"$numberLong":"1238924702841819137"},"date":{"$date":{"$numberLong":"1584217641000"}},"username":"Mellemelg"}
{"_id":{"$oid":"5e6d3e2bd15d2c2ec652e5bb"},"text":"RT @thacondition: This is HARD AS FUCK.","id":{"$numberLong":"1238924703013711874"},"date":{"$date":{"$numberLong":"1584217641000"}},"username":"kaythaking"}
{"_id":{"$oid":"5e6d3e2bd15d2c2ec652e5bc"},"text":"RT @ReadToriko: He was just playing by y’all rules. You want health, you pay for it. \n\nWe all agree that’s a stupid system all of a sudden??","id":{"$numberLong":"1238924703173050368"},"date":{"$date":{"$numberLong":"1584217642000"}},"username":"nessrose"}
{"_id":{"$oid":"5e6d3e2bd15d2c2ec652e5bd"},"text":"RT @PetiteNicoco: Coronavirus hits men harder, women most impacted.","id":{"$numberLong":"1238924703269629952"},"date":{"$date":{"$numberLong":"1584217642000"}},"username":"ZeeTeeAy"}
{"_id":{"$oid":"5e6d3e2bd15d2c2ec652e5be"},"text":"RT @infobeautiful: Our #coronavirus #infographic data pack gathers the best charts in one place &amp; adds some of our own. More: https://t.co/…","id":{"$numberLong":"1238924703294767105"},"date":{"$date":{"$numberLong":"1584217642000"}},"username":"sladedesign"}
{"_id":{"$oid":"5e6d3e2bd15d2c2ec652e5bf"},"text":"RT @mog7546: #Trump CLAIMED his #CORONAVIRUS TEST results won’t be available for another day\n\nJUST ANOTHER LIE\n\nIt takes TWO HOURS\n\ntypical…","id":{"$numberLong":"1238924703475077120"},"date":{"$date":{"$numberLong":"1584217642000"}},"username":"ResistOwl"}
{"_id":{"$oid":"5e6d3e2bd15d2c2ec652e5c0"},"text":"RT @ccarolinekruer: Remember this when someone says “this shouldn’t be political.” \n\nThen tell me why 40 Republicans just voted against sav…","id":{"$numberLong":"1238924703378571265"},"date":{"$date":{"$numberLong":"1584217642000"}},"username":"LenayLove"}
{"_id":{"$oid":"5e6d3e2bd15d2c2ec652e5c1"},"text":"RT @barbaradigi: Italy is facing the most dangerous emergency of our times. IC beds in hospitals are full and doctors are forced to choose…","id":{"$numberLong":"1238924703781265408"},"date":{"$date":{"$numberLong":"1584217642000"}},"username":"ErikaOndrusova"}
{"_id":{"$oid":"5e6d3e2bd15d2c2ec652e5c2"},"text":"RT @elissakh: go away #coronavirus 🤣🤣🤣🤣 https://t.co/OyOPxuaK9v","id":{"$numberLong":"1238924703844139011"},"date":{"$date":{"$numberLong":"1584217642000"}},"username":"AliDm27"}
{"_id":{"$oid":"5e6d3e2bd15d2c2ec652e5c3"},"text":"RT @hxhassan: More background on preventing congregations during extreme weather conditions, through the daily call for prayers. This pract…","id":{"$numberLong":"1238924703827361794"},"date":{"$date":{"$numberLong":"1584217642000"}},"username":"heshaaam"}
{"_id":{"$oid":"5e6d3e2bd15d2c2ec652e5c4"},"text":"RT @JRockTigers: This has Depopulation weapon written all over it. https://t.co/6nvZjuDJAG","id":{"$numberLong":"1238924703965691904"},"date":{"$date":{"$numberLong":"1584217642000"}},"username":"CmdrKoenigMoon"}
{"_id":{"$oid":"5e6d3e2bd15d2c2ec652e5c5"},"text":"RT @thacondition: This is HARD AS FUCK.","id":{"$numberLong":"1238924704007806977"},"date":{"$date":{"$numberLong":"1584217642000"}},"username":"ajay02131"}
{"_id":{"$oid":"5e6d3e2bd15d2c2ec652e5c6"},"text":"Someone spray the anti horny spray to me NOW","id":{"$numberLong":"1238924703990870016"},"date":{"$date":{"$numberLong":"1584217642000"}},"username":"igog_1"}
{"_id":{"$oid":"5e6d3e2bd15d2c2ec652e5c7"},"text":"RT @djdommb: Spread the good details just like you spread the negative ones","id":{"$numberLong":"1238924704011911170"},"date":{"$date":{"$numberLong":"1584217642000"}},"username":"octoberwalls"}
{"_id":{"$oid":"5e6d3e2bd15d2c2ec652e5c8"},"text":"RT @UniteCountryPAC: Joe Biden’s “policy blueprint features a lengthy list of related provisions...  and even includes a \"health crisis foo…","id":{"$numberLong":"1238924704166981632"},"date":{"$date":{"$numberLong":"1584217642000"}},"username":"Kat4Obama"}
{"_id":{"$oid":"5e6d3e2bd15d2c2ec652e5c9"},"text":"RT @_theghettomonk: Not enough praise has gone to medical professionals worldwide. From those in the labs to those bedside","id":{"$numberLong":"1238924704297005056"},"date":{"$date":{"$numberLong":"1584217642000"}},"username":"jessi7elyn"}
{"_id":{"$oid":"5e6d3e2bd15d2c2ec652e5ca"},"text":"You people who are cleaning out the stores are gonna make my job hell for no reason. I already work near 2 hours ov… https://t.co/KRmikvbE70","id":{"$numberLong":"1238924704297242638"},"date":{"$date":{"$numberLong":"1584217642000"}},"username":"BMANvXIII"}
{"_id":{"$oid":"5e6d3e2bd15d2c2ec652e5cb"},"text":"RT @TeaPainUSA: Democrats considered startin' a rumor that Vladimir Putin and Donald Trump are workin' together to use the #Coronavirus to…","id":{"$numberLong":"1238924704502689792"},"date":{"$date":{"$numberLong":"1584217642000"}},"username":"kenn264"}
{"_id":{"$oid":"5e6d3e2bd15d2c2ec652e5cc"},"text":"RT @SKYRIDER4538: Exactly!\nThat’s what experts said as well. It’s expected for the numbers to rise because now were #TestingTestingTesting…","id":{"$numberLong":"1238924704620183552"},"date":{"$date":{"$numberLong":"1584217642000"}},"username":"marieatackett"}
{"_id":{"$oid":"5e6d3e2cd15d2c2ec652e5cd"},"text":"RT @globalstreetart: #coronavirus but keep it #sexy by @pobel.no in Bryne, Norway.\n---\n#GlobalStreetArt #StreetArt #PaintedCities https://t…","id":{"$numberLong":"1238924704649482240"},"date":{"$date":{"$numberLong":"1584217642000"}},"username":"MargauxLgi"}
{"_id":{"$oid":"5e6d3e2cd15d2c2ec652e5ce"},"text":"RT @thacondition: This is HARD AS FUCK.","id":{"$numberLong":"1238924704771178496"},"date":{"$date":{"$numberLong":"1584217642000"}},"username":"umbreyawnn"}
{"_id":{"$oid":"5e6d3e2cd15d2c2ec652e5cf"},"text":"RT @djdommb: Spread the good details just like you spread the negative ones","id":{"$numberLong":"1238924704951316480"},"date":{"$date":{"$numberLong":"1584217642000"}},"username":"Rachael909"}
{"_id":{"$oid":"5e6d3e2cd15d2c2ec652e5d0"},"text":"RT @ULPresident: We have to do anything and everything to stop this awful virus spreading - these professionals will do their part - do YOU…","id":{"$numberLong":"1238924705094152193"},"date":{"$date":{"$numberLong":"1584217642000"}},"username":"NormaBargary"}
{"_id":{"$oid":"5e6d3e2cd15d2c2ec652e5d1"},"text":"RT @redfishstream: A photo of Chinese medical workers and law enforcement officers riding horses to remote places in the Altai Mountains fo…","id":{"$numberLong":"1238924705173733381"},"date":{"$date":{"$numberLong":"1584217642000"}},"username":"plrbrlvr"}
{"_id":{"$oid":"5e6d3e2cd15d2c2ec652e5d2"},"text":"RT @redfishstream: A photo of Chinese medical workers and law enforcement officers riding horses to remote places in the Altai Mountains fo…","id":{"$numberLong":"1238924705157038080"},"date":{"$date":{"$numberLong":"1584217642000"}},"username":"edward_chilton"}
{"_id":{"$oid":"5e6d3e2cd15d2c2ec652e5d3"},"text":"RT @thacondition: This is HARD AS FUCK.","id":{"$numberLong":"1238924705148567553"},"date":{"$date":{"$numberLong":"1584217642000"}},"username":"BondageHead"}
{"_id":{"$oid":"5e6d3e2cd15d2c2ec652e5d4"},"text":"RT @resist4mykids: Damn!","id":{"$numberLong":"1238924705194786817"},"date":{"$date":{"$numberLong":"1584217642000"}},"username":"DC4Hope"}
{"_id":{"$oid":"5e6d3e2cd15d2c2ec652e5d5"},"text":"RT @_theghettomonk: Not enough praise has gone to medical professionals worldwide. From those in the labs to those bedside","id":{"$numberLong":"1238924705215717376"},"date":{"$date":{"$numberLong":"1584217642000"}},"username":"seabassAF"}
{"_id":{"$oid":"5e6d3e2cd15d2c2ec652e5d6"},"text":"Retweet this or I will literally push myself down the fucking stairs","id":{"$numberLong":"1238924705467437057"},"date":{"$date":{"$numberLong":"1584217642000"}},"username":"CrylieJenner"}
{"_id":{"$oid":"5e6d3e2cd15d2c2ec652e5d7"},"text":"RT @LittleMissFlint: Are you upset about standing in long lines, prices on essentials being raised for profit, and stores running out of th…","id":{"$numberLong":"1238924705882611712"},"date":{"$date":{"$numberLong":"1584217642000"}},"username":"naeoodle_"}
{"_id":{"$oid":"5e6d3e2cd15d2c2ec652e5d8"},"text":"RT @ReadToriko: He was just playing by y’all rules. You want health, you pay for it. \n\nWe all agree that’s a stupid system all of a sudden?…","id":{"$numberLong":"1238924705421287430"},"date":{"$date":{"$numberLong":"1584217642000"}},"username":"brenitude"}
{"_id":{"$oid":"5e6d3e2cd15d2c2ec652e5d9"},"text":"RT @sfpelosi: Watched the House vote when a whirl of blue caught my eye — the blue wave of my mom’s dress as @SpeakerPelosi voted to PASS t…","id":{"$numberLong":"1238924706255982592"},"date":{"$date":{"$numberLong":"1584217642000"}},"username":"LeChatNoire4"}
{"_id":{"$oid":"5e6d3e2cd15d2c2ec652e5da"},"text":"Don't panic buy toilet paper, just learn how to do without it.\nYou'll be much cleaner and probably won't go back to… https://t.co/0GephxEU2i","id":{"$numberLong":"1238924706297896965"},"date":{"$date":{"$numberLong":"1584217642000"}},"username":"TarquinTweedle"}
{"_id":{"$oid":"5e6d3e2cd15d2c2ec652e5db"},"text":"RT @Alissonbecker: I am standing side-by-side with @WHO as they help the world fight #COVID19. Through Being Safe, Smart &amp; Kind we will Be…","id":{"$numberLong":"1238924706524409859"},"date":{"$date":{"$numberLong":"1584217642000"}},"username":"the_Gee_Lad"}
{"_id":{"$oid":"5e6d3e2cd15d2c2ec652e5dc"},"text":"RT @ndboy1996: Brand new Guidance from ODE.  It’s encouraging to the note the recognition for flexibility in these uncharted waters.","id":{"$numberLong":"1238924706490744839"},"date":{"$date":{"$numberLong":"1584217642000"}},"username":"BrickerEdLaw"}
{"_id":{"$oid":"5e6d3e2cd15d2c2ec652e5dd"},"text":"Magnifico! Self-isolating residents in Agrigento, Italy come out on their balconies to boost their spirits with a s… https://t.co/exS0c1NoFO","id":{"$numberLong":"1238924706457235457"},"date":{"$date":{"$numberLong":"1584217642000"}},"username":"copywriterLDN"}
{"_id":{"$oid":"5e6d3e2cd15d2c2ec652e5de"},"text":"RT @JuliaHB1: This. This. This. Please watch and share this BRILLIANT explanation for why schools should NOT be closed yet and why that wil…","id":{"$numberLong":"1238924706557943808"},"date":{"$date":{"$numberLong":"1584217642000"}},"username":"XkeepsmilinX"}
{"_id":{"$oid":"5e6d3e2cd15d2c2ec652e5df"},"text":"RT @iandonald_psych: 1. The govt strategy on #Coronavirus is more refined than those used in other countries and potentially very effective…","id":{"$numberLong":"1238924707514245121"},"date":{"$date":{"$numberLong":"1584217643000"}},"username":"AbdelQaader"}
{"_id":{"$oid":"5e6d3e2cd15d2c2ec652e5e0"},"text":"RT @YanniKouts: #BREAKING -- #Spain PM Sánchez announces state of national emergency, orders shutdown of all commercial activities except f…","id":{"$numberLong":"1238924707451359236"},"date":{"$date":{"$numberLong":"1584217643000"}},"username":"PietroLagana"}
{"_id":{"$oid":"5e6d3e2cd15d2c2ec652e5e1"},"text":"RT @ETCanada: .@billmaher tells viewers that @RealTimers will be going on an unexpected hiatus over #coronavirus concerns https://t.co/Th22…","id":{"$numberLong":"1238924707694391297"},"date":{"$date":{"$numberLong":"1584217643000"}},"username":"steveconnieWood"}
{"_id":{"$oid":"5e6d3e2cd15d2c2ec652e5e2"},"text":"RT @thacondition: This is HARD AS FUCK.","id":{"$numberLong":"1238924707396833281"},"date":{"$date":{"$numberLong":"1584217643000"}},"username":"T_sully42"}
{"_id":{"$oid":"5e6d3e2cd15d2c2ec652e5e3"},"text":"RT @thacondition: This is HARD AS FUCK.","id":{"$numberLong":"1238924707723915269"},"date":{"$date":{"$numberLong":"1584217643000"}},"username":"vian_jao"}
{"_id":{"$oid":"5e6d3e2cd15d2c2ec652e5e4"},"text":"RT @djdommb: Spread the good details just like you spread the negative ones","id":{"$numberLong":"1238924708030091271"},"date":{"$date":{"$numberLong":"1584217643000"}},"username":"abbytuttle__"}
{"_id":{"$oid":"5e6d3e2cd15d2c2ec652e5e5"},"text":"RT @redfishstream: Chinese medical workers who have been fighting the #coronavirus day and night in Wuhan celebrated the closing of the las…","id":{"$numberLong":"1238924708264980484"},"date":{"$date":{"$numberLong":"1584217643000"}},"username":"mariemarmottes"}
{"_id":{"$oid":"5e6d3e2cd15d2c2ec652e5e6"},"text":"RT @thacondition: This is HARD AS FUCK.","id":{"$numberLong":"1238924708315193344"},"date":{"$date":{"$numberLong":"1584217643000"}},"username":"sabyiu"}
{"_id":{"$oid":"5e6d3e2cd15d2c2ec652e5e7"},"text":"RT @ReadToriko: He was just playing by y’all rules. You want health, you pay for it. \n\nWe all agree that’s a stupid system all of a sudden??","id":{"$numberLong":"1238924708306960384"},"date":{"$date":{"$numberLong":"1584217643000"}},"username":"Sisiphothegift"}
{"_id":{"$oid":"5e6d3e2cd15d2c2ec652e5e8"},"text":"RT @murshedz: Reporters ought to be asking - how did RNC Chairwoman Ronna McDaniel get access to the test for #coronavirus? https://t.co/Dw…","id":{"$numberLong":"1238924708478889984"},"date":{"$date":{"$numberLong":"1584217643000"}},"username":"BridgetOShea3"}
{"_id":{"$oid":"5e6d3e2cd15d2c2ec652e5e9"},"text":"RT @djdommb: Spread the good details just like you spread the negative ones","id":{"$numberLong":"1238924708462166020"},"date":{"$date":{"$numberLong":"1584217643000"}},"username":"___Dessyy"}
{"_id":{"$oid":"5e6d3e2cd15d2c2ec652e5ea"},"text":"RT @amlcarroll: Special shout out to the fabulous @LauraLynnHouse team for your incredible commitment and support during #COVIDー19 #teamwork","id":{"$numberLong":"1238924708428632069"},"date":{"$date":{"$numberLong":"1584217643000"}},"username":"rekob"}
{"_id":{"$oid":"5e6d3e2cd15d2c2ec652e5eb"},"text":"RT @StevieBrexit: Lawyers and campaigners call for HUNDREDS of immigration centres detainees to be released because of fears they will cont…","id":{"$numberLong":"1238924708856451074"},"date":{"$date":{"$numberLong":"1584217643000"}},"username":"anne_luckhurst"}
{"_id":{"$oid":"5e6d3e2cd15d2c2ec652e5ec"},"text":"\"Coronavirus: Spain announces nationwide lockdown, France to shut down shops\" #Coronavirus https://t.co/YDWH9JcnRQ","id":{"$numberLong":"1238924708608905216"},"date":{"$date":{"$numberLong":"1584217643000"}},"username":"acbsm1997"}
{"_id":{"$oid":"5e6d3e2cd15d2c2ec652e5ed"},"text":"RT @TheNathanOne: These Australian hospitals have a great sense of humor, they made Wilson for @tomhanks to keep him company during his #Qu…","id":{"$numberLong":"1238924708931874818"},"date":{"$date":{"$numberLong":"1584217643000"}},"username":"mensaforall"}
{"_id":{"$oid":"5e6d3e2dd15d2c2ec652e5ee"},"text":"RT @thacondition: This is HARD AS FUCK.","id":{"$numberLong":"1238924708948717568"},"date":{"$date":{"$numberLong":"1584217643000"}},"username":"SamGoIding"}
{"_id":{"$oid":"5e6d3e2dd15d2c2ec652e5ef"},"text":"RT @redfishstream: A photo of Chinese medical workers and law enforcement officers riding horses to remote places in the Altai Mountains fo…","id":{"$numberLong":"1238924709401591813"},"date":{"$date":{"$numberLong":"1584217643000"}},"username":"ThePosq"}
{"_id":{"$oid":"5e6d3e2dd15d2c2ec652e5f0"},"text":"RT @RGrosjean: Speed is of the essence. We must “Be Ready” for the new #coronavirus today. Look out for the most common symptoms for #COVID…","id":{"$numberLong":"1238924709296852997"},"date":{"$date":{"$numberLong":"1584217643000"}},"username":"marcywoolly"}
{"_id":{"$oid":"5e6d3e2dd15d2c2ec652e5f1"},"text":"RT @ccarolinekruer: Remember this when someone says “this shouldn’t be political.” \n\nThen tell me why 40 Republicans just voted against sav…","id":{"$numberLong":"1238924709955129344"},"date":{"$date":{"$numberLong":"1584217643000"}},"username":"porterr_18"}
{"_id":{"$oid":"5e6d3e2dd15d2c2ec652e5f2"},"text":"RT @ccarolinekruer: Remember this when someone says “this shouldn’t be political.” \n\nThen tell me why 40 Republicans just voted against sav…","id":{"$numberLong":"1238924709888167937"},"date":{"$date":{"$numberLong":"1584217643000"}},"username":"ashleyrose2297"}
{"_id":{"$oid":"5e6d3e2dd15d2c2ec652e5f3"},"text":"RT @jfwong: Xenophobia, racism, and directed hate.\n\nThis is not ok.","id":{"$numberLong":"1238924709879840771"},"date":{"$date":{"$numberLong":"1584217643000"}},"username":"heatherfullerrr"}
{"_id":{"$oid":"5e6d3e2dd15d2c2ec652e5f4"},"text":"RT @gemmaod1: #BillGates bloodlines line up as you’d expect. The Luciferian elite are falling one by one. #WWG1WGA #Coronavirus  https://t.…","id":{"$numberLong":"1238924710324428801"},"date":{"$date":{"$numberLong":"1584217643000"}},"username":"xpanner23"}
{"_id":{"$oid":"5e6d3e2dd15d2c2ec652e5f5"},"text":"If everyone's going to be stuck in their homes...they might as well catch up on some TV-… https://t.co/2CJx7jqTNQ","id":{"$numberLong":"1238924709648949250"},"date":{"$date":{"$numberLong":"1584217643000"}},"username":"rogerking"}
{"_id":{"$oid":"5e6d3e2dd15d2c2ec652e5f6"},"text":"RT @timleberecht: How to Be Alone With Yourself.\nAs \"social distancing\" confines us to our four walls, what can we do and from whom can we…","id":{"$numberLong":"1238924710475436034"},"date":{"$date":{"$numberLong":"1584217643000"}},"username":"miguelariza"}
{"_id":{"$oid":"5e6d3e2dd15d2c2ec652e5f7"},"text":"RT @ReadToriko: He was just playing by y’all rules. You want health, you pay for it. \n\nWe all agree that’s a stupid system all of a sudden??","id":{"$numberLong":"1238924710559256576"},"date":{"$date":{"$numberLong":"1584217643000"}},"username":"josiee_09"}
{"_id":{"$oid":"5e6d3e2dd15d2c2ec652e5f8"},"text":"RT @CurryKhn99: When your grandad starts coughing near you #COVID19 #coronavirus #TomHanks https://t.co/im39ER7Xmr","id":{"$numberLong":"1238924710789988355"},"date":{"$date":{"$numberLong":"1584217643000"}},"username":"_cutyhell"}
{"_id":{"$oid":"5e6d3e2dd15d2c2ec652e5f9"},"text":"RT @NFL_Memes: BREAKING: Dallas Cowboys QB Dak Prescott has tested positive for being overrated. #Coronavirus","id":{"$numberLong":"1238924711414738944"},"date":{"$date":{"$numberLong":"1584217643000"}},"username":"Grindrichgordo"}
{"_id":{"$oid":"5e6d3e2dd15d2c2ec652e5fa"},"text":"RT @LivePDDave1: President Trump speaking right now. Look at all the \"old white guys\" on his #coronavirus task force. 🤦‍♂️ https://t.co/OGl…","id":{"$numberLong":"1238924711670800385"},"date":{"$date":{"$numberLong":"1584217644000"}},"username":"darn_war"}
{"_id":{"$oid":"5e6d3e2dd15d2c2ec652e5fb"},"text":"RT @CarolynBMaloney: If you're at home, self-isolating, and already completed the #2020census online, here are some other ways to spend you…","id":{"$numberLong":"1238924711498854403"},"date":{"$date":{"$numberLong":"1584217643000"}},"username":"kashmirimama"}
{"_id":{"$oid":"5e6d3e2dd15d2c2ec652e5fc"},"text":"Well this blows the Boris \"Herd immunity\" principle out of the water. I suspect we should be following the world he… https://t.co/82gdkpwAid","id":{"$numberLong":"1238924711393976321"},"date":{"$date":{"$numberLong":"1584217643000"}},"username":"MonsterErikJ"}
{"_id":{"$oid":"5e6d3e2dd15d2c2ec652e5fd"},"text":"RT @djdommb: Spread the good details just like you spread the negative ones","id":{"$numberLong":"1238924711834222592"},"date":{"$date":{"$numberLong":"1584217644000"}},"username":"omarpadilla99"}
{"_id":{"$oid":"5e6d3e2dd15d2c2ec652e5fe"},"text":"RT @thacondition: This is HARD AS FUCK.","id":{"$numberLong":"1238924712077447168"},"date":{"$date":{"$numberLong":"1584217644000"}},"username":"insanelyaudrey"}
{"_id":{"$oid":"5e6d3e2dd15d2c2ec652e5ff"},"text":"RT @its_RITAAA: U.S. could never..","id":{"$numberLong":"1238924712152928258"},"date":{"$date":{"$numberLong":"1584217644000"}},"username":"sweetNpetite02"}
{"_id":{"$oid":"5e6d3e2dd15d2c2ec652e600"},"text":"RT @dabeard: The CDC wanted to warn anyone over 60 to stay inside their homes whenever possible, in a measure to save lives from #coronavir…","id":{"$numberLong":"1238924712513806338"},"date":{"$date":{"$numberLong":"1584217644000"}},"username":"klarajk"}
{"_id":{"$oid":"5e6d3e2dd15d2c2ec652e601"},"text":"https://t.co/tgCSbDaWRT here you can see some of our CSR work on infection control.\n\nhttps://t.co/wfpuMDqMcK here,… https://t.co/o0kWM9Z1GO","id":{"$numberLong":"1238924712505479176"},"date":{"$date":{"$numberLong":"1584217644000"}},"username":"leashless"}
{"_id":{"$oid":"5e6d3e2dd15d2c2ec652e602"},"text":"RT @BarryWhyte85: Got sent this; Temple Bar this evening apparently. That area should be forced to close.....\n\n#COVIDー19 #coronavirus https…","id":{"$numberLong":"1238924712752881666"},"date":{"$date":{"$numberLong":"1584217644000"}},"username":"manumartins"}
{"_id":{"$oid":"5e6d3e2ed15d2c2ec652e603"},"text":"RT @trish_regan: US shutting borders w/ UK &amp; Ireland—this is another important step in fighting this crisis. Tho the #coronavirus is alread…","id":{"$numberLong":"1238924713256050689"},"date":{"$date":{"$numberLong":"1584217644000"}},"username":"JoeFreedomLove"}
{"_id":{"$oid":"5e6d3e2ed15d2c2ec652e604"},"text":"RT @thacondition: This is HARD AS FUCK.","id":{"$numberLong":"1238924712971063297"},"date":{"$date":{"$numberLong":"1584217644000"}},"username":"marestelle2"}
{"_id":{"$oid":"5e6d3e2ed15d2c2ec652e605"},"text":"RT @DrDenaGrayson: 🚨BREAKING: #Spain announces nationwide lockdown as #coronavirus cases surge with an additional 1,500 cases in one day an…","id":{"$numberLong":"1238924713210101760"},"date":{"$date":{"$numberLong":"1584217644000"}},"username":"debbie_dease"}
{"_id":{"$oid":"5e6d3e2ed15d2c2ec652e606"},"text":"RT @timleberecht: How to Be Alone With Yourself.\nAs \"social distancing\" confines us to our four walls, what can we do and from whom can we…","id":{"$numberLong":"1238924713184964608"},"date":{"$date":{"$numberLong":"1584217644000"}},"username":"ak081289"}
{"_id":{"$oid":"5e6d3e2ed15d2c2ec652e607"},"text":"RT @Polytikle: #COVID19india #coronavirus\n\nChina Vs Indian. Watch Till d End. https://t.co/hwmlYK3zWA","id":{"$numberLong":"1238924713583194113"},"date":{"$date":{"$numberLong":"1584217644000"}},"username":"inc_ricky"}
{"_id":{"$oid":"5e6d3e2ed15d2c2ec652e608"},"text":"RT @WhoIsClayJames: More than 1/2 of the #coronavirus patients globally have recovered. Let’s spread the good information as well. https://…","id":{"$numberLong":"1238924713914761216"},"date":{"$date":{"$numberLong":"1584217644000"}},"username":"octoberwalls"}
{"_id":{"$oid":"5e6d3e2ed15d2c2ec652e609"},"text":"#USPresident #DonaldTrump just announced to reporters he took a #coronavirus test Friday after the press conference… https://t.co/RVFB9HBgMp","id":{"$numberLong":"1238924713952342016"},"date":{"$date":{"$numberLong":"1584217644000"}},"username":"Ndlotus1"}
{"_id":{"$oid":"5e6d3e2ed15d2c2ec652e60a"},"text":"RT @mir_ocall: Today a first responder died of suspected #coronavirus aged 45. He leaves two children. Here an anaesthetist of 35, infected…","id":{"$numberLong":"1238924713835089921"},"date":{"$date":{"$numberLong":"1584217644000"}},"username":"donegalclaret"}
{"_id":{"$oid":"5e6d3e2ed15d2c2ec652e60b"},"text":"RT @AFunnyValentine: FACT! TRUMP Did Not 'FIRE the Entire White House Pandemic Team'\n\nANOTHER MEDIA LIE\n\n#coronavirus\nhttps://t.co/FhbWxSoY…","id":{"$numberLong":"1238924714204000256"},"date":{"$date":{"$numberLong":"1584217644000"}},"username":"ScottyJ54"}
{"_id":{"$oid":"5e6d3e2ed15d2c2ec652e60c"},"text":"Important Message on COVID-19 Coronavirus🦠 from Charity Fundraising:\n\n* https://t.co/D7OqCVw3os… https://t.co/7Mtn5FgVZJ","id":{"$numberLong":"1238924714187292673"},"date":{"$date":{"$numberLong":"1584217644000"}},"username":"CFR1Fundraising"}
{"_id":{"$oid":"5e6d3e2ed15d2c2ec652e60d"},"text":"RT @llisjak: This is amazing. The Spanish government, which has been mismanaging the #coronavirus crisis in an almost criminal manner, now…","id":{"$numberLong":"1238924714199994369"},"date":{"$date":{"$numberLong":"1584217644000"}},"username":"Albaguti3"}
{"_id":{"$oid":"5e6d3e2ed15d2c2ec652e60e"},"text":"“Patients in severe condition may need medical ventilators. Ukraine has only 605 of those, according to the health… https://t.co/6b4eR3aofs","id":{"$numberLong":"1238924714556436480"},"date":{"$date":{"$numberLong":"1584217644000"}},"username":"Laurenmgubina"}
{"_id":{"$oid":"5e6d3e2ed15d2c2ec652e60f"},"text":"RT @ccarolinekruer: Remember this when someone says “this shouldn’t be political.” \n\nThen tell me why 40 Republicans just voted against sav…","id":{"$numberLong":"1238924714753421312"},"date":{"$date":{"$numberLong":"1584217644000"}},"username":"lena316"}
{"_id":{"$oid":"5e6d3e2ed15d2c2ec652e610"},"text":"RT @CPHO_Canada: 1/3 #Socialdistancing is an important contribution that everyone can make to 🇨🇦’s #COVID19 #coronavirus #pandemic control…","id":{"$numberLong":"1238924715105890304"},"date":{"$date":{"$numberLong":"1584217644000"}},"username":"BradWardFight"}
{"_id":{"$oid":"5e6d3e2ed15d2c2ec652e611"},"text":"RT @JGilliam_SEAL: DONT BE ALARMED when US #Covid_19 numbers skyrocket over the next week. The numbers will spike now because more tests ar…","id":{"$numberLong":"1238924715189731329"},"date":{"$date":{"$numberLong":"1584217644000"}},"username":"MulletCyber"}
{"_id":{"$oid":"5e6d3e2ed15d2c2ec652e612"},"text":"RT @MoggMentum: People need to remember that Twitter does not represent Britain. If it did, we would currently have Jeremy Corbyn as PM and…","id":{"$numberLong":"1238924715185639430"},"date":{"$date":{"$numberLong":"1584217644000"}},"username":"annheron41"}
{"_id":{"$oid":"5e6d3e2ed15d2c2ec652e613"},"text":"RT @NewTimesRwanda: SEEN IN KIGALI: To prevent the risk of #Coronavirus outbreak, passengers at the Kigali Bus Park have to wash their hand…","id":{"$numberLong":"1238924715332231169"},"date":{"$date":{"$numberLong":"1584217644000"}},"username":"lailakasuri"}
{"_id":{"$oid":"5e6d3e2ed15d2c2ec652e614"},"text":"RT @WHO: There are simple things we each must do to protect ourselves from #COVID19, including 👐 washing with 🧼 &amp; 💦 or alcohol-based rub.\nW…","id":{"$numberLong":"1238924715483267072"},"date":{"$date":{"$numberLong":"1584217644000"}},"username":"NagyErn6"}
{"_id":{"$oid":"5e6d3e2ed15d2c2ec652e615"},"text":"RT @thacondition: This is HARD AS FUCK. https://t.co/B7mFPnNEZf","id":{"$numberLong":"1238924715407769600"},"date":{"$date":{"$numberLong":"1584217644000"}},"username":"MtyGalvatron"}
{"_id":{"$oid":"5e6d3e2ed15d2c2ec652e616"},"text":"RT @ChinaDaily: #BREAKING France will close all restaurant, cafes, cinemas and clubs to combat the spread of the novel #coronavirus, the co…","id":{"$numberLong":"1238924715571503104"},"date":{"$date":{"$numberLong":"1584217644000"}},"username":"Her_Nimo"}
{"_id":{"$oid":"5e6d3e2ed15d2c2ec652e617"},"text":"RT @StormIsUponUs: There are 1,600 cases of #CoronaVirus in the US. \n- 1% of cases (16) are famous politicians or celebrities. \n- 0.00041%…","id":{"$numberLong":"1238924715713949696"},"date":{"$date":{"$numberLong":"1584217644000"}},"username":"cultcommoncore"}
{"_id":{"$oid":"5e6d3e2ed15d2c2ec652e618"},"text":"RT @redfishstream: A photo of Chinese medical workers and law enforcement officers riding horses to remote places in the Altai Mountains fo…","id":{"$numberLong":"1238924715676372995"},"date":{"$date":{"$numberLong":"1584217644000"}},"username":"letterfrmangela"}
{"_id":{"$oid":"5e6d3e2ed15d2c2ec652e619"},"text":"RT @bigredwavenow: .@flissdesigns Coronavirus: New Zealand issues self-isolation for international arrivals #Coronavirus https://t.co/7U1x6…","id":{"$numberLong":"1238924716187893760"},"date":{"$date":{"$numberLong":"1584217645000"}},"username":"TaylorMcNeal6"}
{"_id":{"$oid":"5e6d3e2ed15d2c2ec652e61a"},"text":"RT @GHS: The following countries &amp; territories have recently reported their first cases of #COVID19: \n\n🇨🇺 Cuba\n🇪🇹 Ethiopia\n🇬🇦 Gabon\n🇬🇭 Ghan…","id":{"$numberLong":"1238924716695531527"},"date":{"$date":{"$numberLong":"1584217645000"}},"username":"SANTIBANES210"}
{"_id":{"$oid":"5e6d3e2ed15d2c2ec652e61b"},"text":"RT @Xarus4: @geertwilderspvv @thierrybaudet this is happening in Italy. Please use this lesson to prevent uncontrolled spread of the virus…","id":{"$numberLong":"1238924716582350851"},"date":{"$date":{"$numberLong":"1584217645000"}},"username":"HooidonkJan"}
{"_id":{"$oid":"5e6d3e2ed15d2c2ec652e61c"},"text":"RT @epenser: On mate, on prend des notes, on partage. GO GO GO !!!","id":{"$numberLong":"1238924716620025856"},"date":{"$date":{"$numberLong":"1584217645000"}},"username":"DebriefDeMorgan"}
{"_id":{"$oid":"5e6d3e2ed15d2c2ec652e61d"},"text":"RT @CountyofLA: #COVID19 Update\n\n@lapublichealth has confirmed 11 new cases in LA County. Total confirmed cases= 53\n\nSocial distancing is t…","id":{"$numberLong":"1238924716968050688"},"date":{"$date":{"$numberLong":"1584217645000"}},"username":"lindshelens"}
{"_id":{"$oid":"5e6d3e2fd15d2c2ec652e61e"},"text":"RT @LittleMissFlint: Are you upset about standing in long lines, prices on essentials being raised for profit, and stores running out of th…","id":{"$numberLong":"1238924717307953154"},"date":{"$date":{"$numberLong":"1584217645000"}},"username":"tresleches_mami"}
{"_id":{"$oid":"5e6d3e2fd15d2c2ec652e61f"},"text":"RT @thacondition: This is HARD AS FUCK.","id":{"$numberLong":"1238924717475561472"},"date":{"$date":{"$numberLong":"1584217645000"}},"username":"imswinging"}
{"_id":{"$oid":"5e6d3e2fd15d2c2ec652e620"},"text":"RT @OliviaWebbC: My new op-ed in @BuzzFeedNews talking about how decades of consolidation weakened our supply chains and ability to make dr…","id":{"$numberLong":"1238924717634908160"},"date":{"$date":{"$numberLong":"1584217645000"}},"username":"peaceinpols"}
{"_id":{"$oid":"5e6d3e2fd15d2c2ec652e621"},"text":"RT @WHO: How to handrub?\n\nUse alcohol-based handrub 🧴 for 20-30 seconds \n\n#SafeHands #coronavirus #COVID19 https://t.co/q1UAqmCTcN","id":{"$numberLong":"1238924717496696840"},"date":{"$date":{"$numberLong":"1584217645000"}},"username":"joellelynn"}
{"_id":{"$oid":"5e6d3e2fd15d2c2ec652e622"},"text":"Absolutely disgusting","id":{"$numberLong":"1238924717702119427"},"date":{"$date":{"$numberLong":"1584217645000"}},"username":"SteeleSilver"}
{"_id":{"$oid":"5e6d3e2fd15d2c2ec652e623"},"text":"RT @ramnarayan_sr: When Iran Government was not well equipped to test Indians stranded in Iran for #CoronaVirus\n\nGovt of India sent an enti…","id":{"$numberLong":"1238924718075330560"},"date":{"$date":{"$numberLong":"1584217645000"}},"username":"sameerpithadia"}
{"_id":{"$oid":"5e6d3e2fd15d2c2ec652e624"},"text":"RT @CarolineDrury12: Sullivan’s island idea of social distancing! #coronavirus @HolyCitySinner https://t.co/hf1SpZjTTT","id":{"$numberLong":"1238924717794512897"},"date":{"$date":{"$numberLong":"1584217645000"}},"username":"multimarymc"}
{"_id":{"$oid":"5e6d3e2fd15d2c2ec652e625"},"text":"RT @ccarolinekruer: Remember this when someone says “this shouldn’t be political.” \n\nThen tell me why 40 Republicans just voted against sav…","id":{"$numberLong":"1238924718247276544"},"date":{"$date":{"$numberLong":"1584217645000"}},"username":"bobbygianna"}
{"_id":{"$oid":"5e6d3e2fd15d2c2ec652e626"},"text":"RT @AndyOstroy: About the #coronavirus...\n\n@realDonaldTrump...\nFeb 28: \"a new hoax\"\nMar 13: \"a #NationalEmergency'\n\nThe most pathologically…","id":{"$numberLong":"1238924718503104512"},"date":{"$date":{"$numberLong":"1584217645000"}},"username":"magicking78x"}
{"_id":{"$oid":"5e6d3e2fd15d2c2ec652e627"},"text":"RT @WHO: Honor caretakers and healthcare workers supporting people affected with #COVID19 in your community.\n\nAcknowledge the role they pla…","id":{"$numberLong":"1238924718650032129"},"date":{"$date":{"$numberLong":"1584217645000"}},"username":"iNorahS"}
{"_id":{"$oid":"5e6d3e2fd15d2c2ec652e628"},"text":"RT @hxhassan: Eerie. The Muslim call for prayers in Kuwait replaces “hayya ala-salat” (come to prayer) &amp; “hayya ala falah” (come to success…","id":{"$numberLong":"1238924719073738752"},"date":{"$date":{"$numberLong":"1584217645000"}},"username":"tweeter_anita"}
{"_id":{"$oid":"5e6d3e2fd15d2c2ec652e629"},"text":"RT @sahouraxo: Holy moly.\n\nMassive anti-government protests in #Paris, #France today, defying #coronavirus lockdown.\n\nBut barely a peep fro…","id":{"$numberLong":"1238924719115718660"},"date":{"$date":{"$numberLong":"1584217645000"}},"username":"madpatriot78"}
{"_id":{"$oid":"5e6d3e2fd15d2c2ec652e62a"},"text":"#Coronavirus: Five new cases brings #COVID19 total in north to 34\nhttps://t.co/sbJQR6Kj5d #SARSCoV2\n#Covid_19ireland","id":{"$numberLong":"1238924719493197824"},"date":{"$date":{"$numberLong":"1584217645000"}},"username":"derryjournal"}
{"_id":{"$oid":"5e6d3e2fd15d2c2ec652e62b"},"text":"Our future at this rate 🤦‍♂️😂 #toiletpaper #coronavirus https://t.co/3SVL3DqPoH","id":{"$numberLong":"1238924719216361472"},"date":{"$date":{"$numberLong":"1584217645000"}},"username":"Justin_McGill"}
{"_id":{"$oid":"5e6d3e2fd15d2c2ec652e62c"},"text":"RT @sandyaschneider: Mexico is going to become a cluster F*ck for #coronavirus. The government is behaving like the virus isn't in the coun…","id":{"$numberLong":"1238924719782383617"},"date":{"$date":{"$numberLong":"1584217645000"}},"username":"catalyst_equine"}
{"_id":{"$oid":"5e6d3e2fd15d2c2ec652e62d"},"text":"RT @thacondition: This is HARD AS FUCK.","id":{"$numberLong":"1238924719719690245"},"date":{"$date":{"$numberLong":"1584217645000"}},"username":"EliasCarstairs"}
{"_id":{"$oid":"5e6d3e2fd15d2c2ec652e62e"},"text":"RT @Sanju_Verma_: 10thDec2019-1st case of #coronavirus in Wuhan\n31stDec-China calls it 'pneumonia'\n\n3rdJan2020- China forces Doctor #Li to…","id":{"$numberLong":"1238924720214548480"},"date":{"$date":{"$numberLong":"1584217646000"}},"username":"trollpappu2"}
{"_id":{"$oid":"5e6d3e2fd15d2c2ec652e62f"},"text":"RT @LNsour5: A message from Gaza/Palestine to the world! \n#CoronaVirusUpdates \n#كورونا #coronavirus https://t.co/JjKkY7kF7F","id":{"$numberLong":"1238924720315207681"},"date":{"$date":{"$numberLong":"1584217646000"}},"username":"suz1233madrid"}
{"_id":{"$oid":"5e6d3e2fd15d2c2ec652e630"},"text":"RT @gsrescueelite: * Crufts Update * \nSadly we did suffer due to the #coronavirus as did the majority of the stands but we still had a lot…","id":{"$numberLong":"1238924720281653254"},"date":{"$date":{"$numberLong":"1584217646000"}},"username":"pat35083377"}
{"_id":{"$oid":"5e6d3e2fd15d2c2ec652e631"},"text":"RT @JohnStossel: Some stores are running out of basic goods because frightened people are hoarding stuff because of #coronavirus.  \n\nOne so…","id":{"$numberLong":"1238924720403369986"},"date":{"$date":{"$numberLong":"1584217646000"}},"username":"C4CEO"}
{"_id":{"$oid":"5e6d3e2fd15d2c2ec652e632"},"text":"RT @thacondition: This is HARD AS FUCK.","id":{"$numberLong":"1238924720587898882"},"date":{"$date":{"$numberLong":"1584217646000"}},"username":"BreadBoyBeggly"}
{"_id":{"$oid":"5e6d3e2fd15d2c2ec652e633"},"text":"Good info! Thanks for sharing.","id":{"$numberLong":"1238924720617259010"},"date":{"$date":{"$numberLong":"1584217646000"}},"username":"NurseyNoodles"}
{"_id":{"$oid":"5e6d3e2fd15d2c2ec652e634"},"text":"RT @djdommb: Spread the good details just like you spread the negative ones","id":{"$numberLong":"1238924720495566851"},"date":{"$date":{"$numberLong":"1584217646000"}},"username":"YoBalhico"}
{"_id":{"$oid":"5e6d3e2fd15d2c2ec652e635"},"text":"Shopper ‘mugged’ for toilet roll as #coronavirus panic-buying grips UK\n\nhttps://t.co/ljlkSNjxw0 https://t.co/HzBo5kybs2","id":{"$numberLong":"1238924720558551043"},"date":{"$date":{"$numberLong":"1584217646000"}},"username":"ScottishSun"}
{"_id":{"$oid":"5e6d3e2fd15d2c2ec652e636"},"text":"RT @RVAwonk: Yikes. Japan has reported its first case of a person becoming *reinfected* with #coronavirus after appearing to make a full re…","id":{"$numberLong":"1238924720881504258"},"date":{"$date":{"$numberLong":"1584217646000"}},"username":"DC4Hope"}
{"_id":{"$oid":"5e6d3e30d15d2c2ec652e637"},"text":"RT @drvyom: The most dangerous #coronavirus myth is that only old/sick people will die. When this disease consumes every ICU bed, anaesthet…","id":{"$numberLong":"1238924721544192003"},"date":{"$date":{"$numberLong":"1584217646000"}},"username":"LrningInstigatr"}
{"_id":{"$oid":"5e6d3e30d15d2c2ec652e638"},"text":"RT @AbasAslani: A young #Iran-ian clergy, voluntarily helping #CoronaVirus patients in a hospital in Qom, lost his pregnant wife with twins…","id":{"$numberLong":"1238924721598672900"},"date":{"$date":{"$numberLong":"1584217646000"}},"username":"BarmakN"}
{"_id":{"$oid":"5e6d3e30d15d2c2ec652e639"},"text":"RT @joncoopertweets: Isn’t it ironic that two of the #coronavirus hotspots are the the Trump White House and Mar-a-Lago? 🦠","id":{"$numberLong":"1238924722101989376"},"date":{"$date":{"$numberLong":"1584217646000"}},"username":"KathleenRoche59"}
{"_id":{"$oid":"5e6d3e30d15d2c2ec652e63a"},"text":"RT @thacondition: This is HARD AS FUCK.","id":{"$numberLong":"1238924722127228931"},"date":{"$date":{"$numberLong":"1584217646000"}},"username":"goldashes_"}
{"_id":{"$oid":"5e6d3e30d15d2c2ec652e63b"},"text":"RT @nasw: #Socialworkers: Worried About #COVID19? #NASW cares about you. We’ve prepared a #coronavirus resource page w/reliable information…","id":{"$numberLong":"1238924722290614272"},"date":{"$date":{"$numberLong":"1584217646000"}},"username":"TimSchmaltz"}
{"_id":{"$oid":"5e6d3e30d15d2c2ec652e63c"},"text":"RT @dabeard: The CDC wanted to warn anyone over 60 to stay inside their homes whenever possible, in a measure to save lives from #coronavir…","id":{"$numberLong":"1238924722173329409"},"date":{"$date":{"$numberLong":"1584217646000"}},"username":"Zekesgirl1959"}
{"_id":{"$oid":"5e6d3e30d15d2c2ec652e63d"},"text":"RT @realalexkapp: I just spent hours waiting, outside, in the cold and rain, at Cedars Sinai Hospital in Los Angeles waiting to get my daug…","id":{"$numberLong":"1238924722374615043"},"date":{"$date":{"$numberLong":"1584217646000"}},"username":"giioldbroad"}
{"_id":{"$oid":"5e6d3e30d15d2c2ec652e63e"},"text":"RT @redfishstream: A photo of Chinese medical workers and law enforcement officers riding horses to remote places in the Altai Mountains fo…","id":{"$numberLong":"1238924722425016320"},"date":{"$date":{"$numberLong":"1584217646000"}},"username":"SubtleCatfish"}
{"_id":{"$oid":"5e6d3e30d15d2c2ec652e63f"},"text":"RT @Reuters: Trump says he has taken #coronavirus test, extends travel ban to Britain and Ireland to try to contain pandemic https://t.co/7…","id":{"$numberLong":"1238924722311770114"},"date":{"$date":{"$numberLong":"1584217646000"}},"username":"aklen"}
{"_id":{"$oid":"5e6d3e30d15d2c2ec652e640"},"text":"RT @YanniKouts: #BREAKING -- #Spain PM Sánchez announces state of national emergency, orders shutdown of all commercial activities except f…","id":{"$numberLong":"1238924722571788290"},"date":{"$date":{"$numberLong":"1584217646000"}},"username":"mystirios70"}
{"_id":{"$oid":"5e6d3e30d15d2c2ec652e641"},"text":"RT @WHO: \"Pandemic is not a word to use lightly or carelessly. It is a word that, if misused, can cause unreasonable fear, or unjustified a…","id":{"$numberLong":"1238924722760384512"},"date":{"$date":{"$numberLong":"1584217646000"}},"username":"NatashaPetters3"}
{"_id":{"$oid":"5e6d3e30d15d2c2ec652e642"},"text":"I'm my country we wash hands","id":{"$numberLong":"1238924722588483584"},"date":{"$date":{"$numberLong":"1584217646000"}},"username":"Itz_SK"}
{"_id":{"$oid":"5e6d3e30d15d2c2ec652e643"},"text":"RT @redfishstream: Chinese medical workers who have been fighting the #coronavirus day and night in Wuhan celebrated the closing of the las…","id":{"$numberLong":"1238924722764644353"},"date":{"$date":{"$numberLong":"1584217646000"}},"username":"Agrosecurity411"}
{"_id":{"$oid":"5e6d3e30d15d2c2ec652e644"},"text":"RT @GandalfIl: #Lagarde Fuck you 🖕🏼🇪🇺\n@Europarl_IT @DipPoliticheUE @EU_Commission #Lagardedimettiti #LagardeResign #LagardeVirus \n#COVIDー19…","id":{"$numberLong":"1238924722898898944"},"date":{"$date":{"$numberLong":"1584217646000"}},"username":"GBestlap"}
{"_id":{"$oid":"5e6d3e30d15d2c2ec652e645"},"text":"RT @otto_lanza: #coronavirus Italy update: Codogno, the first town to face lockdown about three weeks ago, just reported that the number of…","id":{"$numberLong":"1238924722785615873"},"date":{"$date":{"$numberLong":"1584217646000"}},"username":"BronSan_"}
{"_id":{"$oid":"5e6d3e30d15d2c2ec652e646"},"text":"RT @redfishstream: Chinese medical workers who have been fighting the #coronavirus day and night in Wuhan celebrated the closing of the las…","id":{"$numberLong":"1238924723137937410"},"date":{"$date":{"$numberLong":"1584217646000"}},"username":"facecard7"}
{"_id":{"$oid":"5e6d3e30d15d2c2ec652e647"},"text":"RT @thacondition: This is HARD AS FUCK.","id":{"$numberLong":"1238924723188359169"},"date":{"$date":{"$numberLong":"1584217646000"}},"username":"DanielaSalomonA"}
{"_id":{"$oid":"5e6d3e30d15d2c2ec652e648"},"text":"RT @ReadToriko: He was just playing by y’all rules. You want health, you pay for it. \n\nWe all agree that’s a stupid system all of a sudden??","id":{"$numberLong":"1238924723414863872"},"date":{"$date":{"$numberLong":"1584217646000"}},"username":"lilvaal"}
{"_id":{"$oid":"5e6d3e30d15d2c2ec652e649"},"text":"RT @ANI: Odisha:A person has been arrested on charges of posting fake news on social media on outbreak of #coronavirus,in Rayagada.Police s…","id":{"$numberLong":"1238924723708235776"},"date":{"$date":{"$numberLong":"1584217646000"}},"username":"AnkitGoluSajwan"}
{"_id":{"$oid":"5e6d3e30d15d2c2ec652e64a"},"text":"RT @LincolnsBible: No snark.\nMar-a-Lago is revealing itself to be a hot spot for the virus.","id":{"$numberLong":"1238924723746009088"},"date":{"$date":{"$numberLong":"1584217646000"}},"username":"atypicalblonde"}
{"_id":{"$oid":"5e6d3e30d15d2c2ec652e64b"},"text":"RT @thacondition: This is HARD AS FUCK.","id":{"$numberLong":"1238924723721048065"},"date":{"$date":{"$numberLong":"1584217646000"}},"username":"M84889735"}
{"_id":{"$oid":"5e6d3e30d15d2c2ec652e64c"},"text":"RT @ccarolinekruer: Remember this when someone says “this shouldn’t be political.” \n\nThen tell me why 40 Republicans just voted against sav…","id":{"$numberLong":"1238924723758792705"},"date":{"$date":{"$numberLong":"1584217646000"}},"username":"goth_gunnywolf"}
{"_id":{"$oid":"5e6d3e30d15d2c2ec652e64d"},"text":"RT @ccarolinekruer: Remember this when someone says “this shouldn’t be political.” \n\nThen tell me why 40 Republicans just voted against sav…","id":{"$numberLong":"1238924723859460096"},"date":{"$date":{"$numberLong":"1584217646000"}},"username":"wbkash"}
{"_id":{"$oid":"5e6d3e30d15d2c2ec652e64e"},"text":"RT @ninatypewriter: #Coronavirus #COVID19 GOVERNOR FINALLY ADMITS COMMUNITY SPREAD IN FLORIDA\nFollow my lists for news:\nHEALTH https://t.co…","id":{"$numberLong":"1238924724018839554"},"date":{"$date":{"$numberLong":"1584217646000"}},"username":"ChicagoBernie"}
{"_id":{"$oid":"5e6d3e30d15d2c2ec652e64f"},"text":"RT @redfishstream: Chinese medical workers who have been fighting the #coronavirus day and night in Wuhan celebrated the closing of the las…","id":{"$numberLong":"1238924724119486465"},"date":{"$date":{"$numberLong":"1584217646000"}},"username":"ericovel"}
{"_id":{"$oid":"5e6d3e30d15d2c2ec652e650"},"text":"RT @thacondition: This is HARD AS FUCK.","id":{"$numberLong":"1238924723909779456"},"date":{"$date":{"$numberLong":"1584217646000"}},"username":"duncw3"}
{"_id":{"$oid":"5e6d3e30d15d2c2ec652e651"},"text":"THIS","id":{"$numberLong":"1238924724446560257"},"date":{"$date":{"$numberLong":"1584217647000"}},"username":"common_sensedoc"}
{"_id":{"$oid":"5e6d3e30d15d2c2ec652e652"},"text":"RT @AntonyTiernan: Please add this picture to your Twitter profile and help direct people to accurate + reputable info about coronavirus #N…","id":{"$numberLong":"1238924724593360897"},"date":{"$date":{"$numberLong":"1584217647000"}},"username":"mandybate"}
{"_id":{"$oid":"5e6d3e30d15d2c2ec652e653"},"text":"RT @Reuters: Trump says he has taken #coronavirus test, extends travel ban to Britain and Ireland to try to contain pandemic https://t.co/7…","id":{"$numberLong":"1238924724585062401"},"date":{"$date":{"$numberLong":"1584217647000"}},"username":"oalfarrabista"}
{"_id":{"$oid":"5e6d3e30d15d2c2ec652e654"},"text":"RT @skwawkbox: The most devastating, tragic and true coronavirus video you'll see today https://t.co/tGXioTLurA","id":{"$numberLong":"1238924724622802944"},"date":{"$date":{"$numberLong":"1584217647000"}},"username":"mike_leckenby"}
{"_id":{"$oid":"5e6d3e30d15d2c2ec652e655"},"text":"RT @christinawilkie: Just In: Republican National Committee Chair Ronna Romney McDaniel went to the hospital last nigh with a fever and flu…","id":{"$numberLong":"1238924724752842754"},"date":{"$date":{"$numberLong":"1584217647000"}},"username":"whoowhooH"}
{"_id":{"$oid":"5e6d3e30d15d2c2ec652e656"},"text":"RT @ccarolinekruer: Remember this when someone says “this shouldn’t be political.” \n\nThen tell me why 40 Republicans just voted against sav…","id":{"$numberLong":"1238924724974972928"},"date":{"$date":{"$numberLong":"1584217647000"}},"username":"___Evelinn"}
{"_id":{"$oid":"5e6d3e30d15d2c2ec652e657"},"text":"RT @IranianRoya: Bushehr, S #Iran \nA man suspected of being #COVID19 positive\nThe covid19 crisis in Iran is out of control due to the regim…","id":{"$numberLong":"1238924724908032002"},"date":{"$date":{"$numberLong":"1584217647000"}},"username":"Karl01113434"}
{"_id":{"$oid":"5e6d3e30d15d2c2ec652e658"},"text":"RT @djdommb: Spread the good details just like you spread the negative ones","id":{"$numberLong":"1238924725147127809"},"date":{"$date":{"$numberLong":"1584217647000"}},"username":"vee_enna_"}
{"_id":{"$oid":"5e6d3e30d15d2c2ec652e659"},"text":"I pray all people, families and countries, (everyone sharing this beautiful and fragile world with us) will grow in… https://t.co/DNzJboiV62","id":{"$numberLong":"1238924725335842816"},"date":{"$date":{"$numberLong":"1584217647000"}},"username":"luminatelynne"}
{"_id":{"$oid":"5e6d3e30d15d2c2ec652e65a"},"text":"RT @NFL_Memes: BREAKING: Dallas Cowboys QB Dak Prescott has tested positive for being overrated. #Coronavirus","id":{"$numberLong":"1238924725373542402"},"date":{"$date":{"$numberLong":"1584217647000"}},"username":"JoeMuhonen"}
{"_id":{"$oid":"5e6d3e30d15d2c2ec652e65b"},"text":"RT @DarrenPlymouth: An Italian compares the obituaries of a local daily newspaper. One on the 9th Feb, the other 13th Mar.\n\nIf you would li…","id":{"$numberLong":"1238924725499375616"},"date":{"$date":{"$numberLong":"1584217647000"}},"username":"Heisenb91740991"}
{"_id":{"$oid":"5e6d3e30d15d2c2ec652e65c"},"text":"RT @BeardedGenius: This 18 seconds is probably the best single piece of advice I’ve heard about the #coronavirus https://t.co/buDs1fhdwL","id":{"$numberLong":"1238924725453295616"},"date":{"$date":{"$numberLong":"1584217647000"}},"username":"broonstunes"}
{"_id":{"$oid":"5e6d3e31d15d2c2ec652e65d"},"text":"@skwawkbox @BorisJohnson @MattHancock  Suppress #coronavirus and you become vulnerable to the second and most deadl… https://t.co/E1t9v42M5R","id":{"$numberLong":"1238924725876862976"},"date":{"$date":{"$numberLong":"1584217647000"}},"username":"SocialistFry"}
{"_id":{"$oid":"5e6d3e31d15d2c2ec652e65e"},"text":"RT @zachbraff: People are dying. He’s got jokes.","id":{"$numberLong":"1238924726283747329"},"date":{"$date":{"$numberLong":"1584217647000"}},"username":"ThatSharonOne"}
{"_id":{"$oid":"5e6d3e31d15d2c2ec652e65f"},"text":"To the people who go to the emergency room because they think they have #coronavirus remember that heart attacks, a… https://t.co/eRbYueF7ho","id":{"$numberLong":"1238924726476644353"},"date":{"$date":{"$numberLong":"1584217647000"}},"username":"ArtyC01"}
{"_id":{"$oid":"5e6d3e31d15d2c2ec652e660"},"text":"NC people, seriously good thread about our current situation. Clear communication. Thank you Sen. Jackson.","id":{"$numberLong":"1238924726652854272"},"date":{"$date":{"$numberLong":"1584217647000"}},"username":"GanzSally"}
{"_id":{"$oid":"5e6d3e31d15d2c2ec652e661"},"text":"RT @thacondition: This is HARD AS FUCK.","id":{"$numberLong":"1238924726564683776"},"date":{"$date":{"$numberLong":"1584217647000"}},"username":"Marcoss_Nunezzz"}
{"_id":{"$oid":"5e6d3e31d15d2c2ec652e662"},"text":"RT @mohamadfakih8: Anyone on our team who takes ill will get full paid leave and all the nutritious Paramount food they need to get well. T…","id":{"$numberLong":"1238924726610931713"},"date":{"$date":{"$numberLong":"1584217647000"}},"username":"asmithtvdsb"}
{"_id":{"$oid":"5e6d3e31d15d2c2ec652e663"},"text":"RT @kapoorkkunal: A friend of mine came back home, a couple of weeks back, after travelling to a few countries. The health minsitry had som…","id":{"$numberLong":"1238924726929485824"},"date":{"$date":{"$numberLong":"1584217647000"}},"username":"Prashan09432058"}
{"_id":{"$oid":"5e6d3e31d15d2c2ec652e664"},"text":"RT @Paula_Piccard: #5G robot help epidemic control\n\n @XHscitech #Robotics #CoronaVirus #Health #MachineLearning #AI #Tech \n\n@MikeQuindazzi…","id":{"$numberLong":"1238924727298768896"},"date":{"$date":{"$numberLong":"1584217647000"}},"username":"Zaratsoga"}
{"_id":{"$oid":"5e6d3e31d15d2c2ec652e665"},"text":"RT @djdommb: Spread the good details just like you spread the negative ones","id":{"$numberLong":"1238924727261020160"},"date":{"$date":{"$numberLong":"1584217647000"}},"username":"Loverle3e"}
{"_id":{"$oid":"5e6d3e31d15d2c2ec652e666"},"text":"RT @thacondition: This is HARD AS FUCK. https://t.co/B7mFPnNEZf","id":{"$numberLong":"1238924727533670402"},"date":{"$date":{"$numberLong":"1584217647000"}},"username":"ayraland"}
{"_id":{"$oid":"5e6d3e31d15d2c2ec652e667"},"text":"RT @Joyce_Karam: The irony: People gather in #Kuwait to watch a #CoronaVirus alert drone telling them not to gather and go home.\n\nNearly 10…","id":{"$numberLong":"1238924727625883653"},"date":{"$date":{"$numberLong":"1584217647000"}},"username":"Gaylorde2018"}
{"_id":{"$oid":"5e6d3e31d15d2c2ec652e668"},"text":"RT @_theghettomonk: Not enough praise has gone to medical professionals worldwide. From those in the labs to those bedside","id":{"$numberLong":"1238924727747358720"},"date":{"$date":{"$numberLong":"1584217647000"}},"username":"richardcjkim"}
{"_id":{"$oid":"5e6d3e31d15d2c2ec652e669"},"text":"RT @thacondition: This is HARD AS FUCK.","id":{"$numberLong":"1238924728150052864"},"date":{"$date":{"$numberLong":"1584217647000"}},"username":"ancientmarinere"}
{"_id":{"$oid":"5e6d3e31d15d2c2ec652e66a"},"text":"RT @thacondition: This is HARD AS FUCK.","id":{"$numberLong":"1238924728422694912"},"date":{"$date":{"$numberLong":"1584217648000"}},"username":"Emmanuel_47_"}
{"_id":{"$oid":"5e6d3e31d15d2c2ec652e66b"},"text":"RT @MSEMA: The Small Business Administration is offering low-interest federal disaster loans for businesses suffering substantial economic…","id":{"$numberLong":"1238924728724791298"},"date":{"$date":{"$numberLong":"1584217648000"}},"username":"CityofMcCombMS"}
{"_id":{"$oid":"5e6d3e31d15d2c2ec652e66c"},"text":"RT @TomFletcher: Here’s an awesome way to help your kids understand why we need to wash our hands. Saw a teacher do this with her class and…","id":{"$numberLong":"1238924728787775490"},"date":{"$date":{"$numberLong":"1584217648000"}},"username":"oyejosefa"}
{"_id":{"$oid":"5e6d3e31d15d2c2ec652e66d"},"text":"RT @SarcasmStardust: I’ve said if before, I’ll say it again, I fucking love the French.","id":{"$numberLong":"1238924729018470402"},"date":{"$date":{"$numberLong":"1584217648000"}},"username":"billm9"}
{"_id":{"$oid":"5e6d3e31d15d2c2ec652e66e"},"text":"RT @SenatorBennet: Last Thursday I urged internet companies to do whatever they could to make broadband accessible to everyone during the #…","id":{"$numberLong":"1238924729274322944"},"date":{"$date":{"$numberLong":"1584217648000"}},"username":"notorioushilary"}
{"_id":{"$oid":"5e6d3e31d15d2c2ec652e66f"},"text":"RT @djdommb: Spread the good details just like you spread the negative ones","id":{"$numberLong":"1238924729559334914"},"date":{"$date":{"$numberLong":"1584217648000"}},"username":"donaldmytrump"}
{"_id":{"$oid":"5e6d3e31d15d2c2ec652e670"},"text":"RT @djdommb: Spread the good details just like you spread the negative ones","id":{"$numberLong":"1238924729605476352"},"date":{"$date":{"$numberLong":"1584217648000"}},"username":"arodriiguezz01"}
{"_id":{"$oid":"5e6d3e31d15d2c2ec652e671"},"text":"RT @djdommb: Spread the good details just like you spread the negative ones","id":{"$numberLong":"1238924729722892288"},"date":{"$date":{"$numberLong":"1584217648000"}},"username":"azarate_18"}
{"_id":{"$oid":"5e6d3e32d15d2c2ec652e672"},"text":"RT @NancyCuene: Vote these congressmen and women out in November. They certainly don't care about their constituents. \n\nVoteBlueToSaveAmeri…","id":{"$numberLong":"1238924729727234055"},"date":{"$date":{"$numberLong":"1584217648000"}},"username":"GappaLeigh"}
{"_id":{"$oid":"5e6d3e32d15d2c2ec652e673"},"text":"Are you prepared to loose your loved ones? #BorisJohnson is ready to sacrifice everybody in the name of Nazi scient… https://t.co/r7uAoDImyR","id":{"$numberLong":"1238924730251587585"},"date":{"$date":{"$numberLong":"1584217648000"}},"username":"IMHOWEB"}
{"_id":{"$oid":"5e6d3e32d15d2c2ec652e674"},"text":"RT @ccarolinekruer: Remember this when someone says “this shouldn’t be political.” \n\nThen tell me why 40 Republicans just voted against sav…","id":{"$numberLong":"1238924730297614349"},"date":{"$date":{"$numberLong":"1584217648000"}},"username":"EdgarLopez36"}
{"_id":{"$oid":"5e6d3e32d15d2c2ec652e675"},"text":"@MegDeforge dad said you were going? Coronavirus: Spain announces nationwide lockdown, France to shut down shops… https://t.co/4u745N86ER","id":{"$numberLong":"1238924730205437953"},"date":{"$date":{"$numberLong":"1584217648000"}},"username":"hiddentalent87"}
{"_id":{"$oid":"5e6d3e32d15d2c2ec652e676"},"text":"RT @redfishstream: Chinese medical workers who have been fighting the #coronavirus day and night in Wuhan celebrated the closing of the las…","id":{"$numberLong":"1238924730704560129"},"date":{"$date":{"$numberLong":"1584217648000"}},"username":"kamijane4"}
{"_id":{"$oid":"5e6d3e32d15d2c2ec652e677"},"text":"RT @WHO: #HealthWorkers,\nfeeling under pressure is a likely experience for you and many of your health workers colleagues.\n\nIt is quite nor…","id":{"$numberLong":"1238924730813616133"},"date":{"$date":{"$numberLong":"1584217648000"}},"username":"iNorahS"}
{"_id":{"$oid":"5e6d3e32d15d2c2ec652e678"},"text":"Love this! #Napoli #coronavirus #togetherness","id":{"$numberLong":"1238924731300143104"},"date":{"$date":{"$numberLong":"1584217648000"}},"username":"CarolineDale3LJ"}
{"_id":{"$oid":"5e6d3e32d15d2c2ec652e679"},"text":"RT @2019_winston: Lets see if our dear @BBCNews starts to report what’s going on in the UK’s hospitals. The 24 year old son of a friend spe…","id":{"$numberLong":"1238924731618910209"},"date":{"$date":{"$numberLong":"1584217648000"}},"username":"LEAPUP1"}
{"_id":{"$oid":"5e6d3e32d15d2c2ec652e67a"},"text":"RT @drharshvardhan: Dear @shubham28242515 hope you’re comfortable in the isolation ward at IDH Infectious Disease Hospital, GSVM Medical Co…","id":{"$numberLong":"1238924731610361856"},"date":{"$date":{"$numberLong":"1584217648000"}},"username":"craft_cuisine"}
{"_id":{"$oid":"5e6d3e32d15d2c2ec652e67b"},"text":"Im worried 😢 my bf gonna go back to Laguna for his studies","id":{"$numberLong":"1238924732168163328"},"date":{"$date":{"$numberLong":"1584217648000"}},"username":"_riltok"}
{"_id":{"$oid":"5e6d3e32d15d2c2ec652e67c"},"text":"RT @ReadToriko: He was just playing by y’all rules. You want health, you pay for it. \n\nWe all agree that’s a stupid system all of a sudden??","id":{"$numberLong":"1238924732449374210"},"date":{"$date":{"$numberLong":"1584217648000"}},"username":"Sequiera337"}
{"_id":{"$oid":"5e6d3e32d15d2c2ec652e67d"},"text":"RT @bobbycblanchard: by my accounting, this is now the most RT'd tweet from The @TexasTribune ever. \n\nhttps://t.co/Z5hN5koqUD","id":{"$numberLong":"1238924732478742529"},"date":{"$date":{"$numberLong":"1584217648000"}},"username":"RichterKay"}
{"_id":{"$oid":"5e6d3e32d15d2c2ec652e67e"},"text":"RT @_theghettomonk: Not enough praise has gone to medical professionals worldwide. From those in the labs to those bedside","id":{"$numberLong":"1238924732755374080"},"date":{"$date":{"$numberLong":"1584217649000"}},"username":"franniehernand"}
{"_id":{"$oid":"5e6d3e32d15d2c2ec652e67f"},"text":"RT @LincolnsBible: No snark.\nMar-a-Lago is revealing itself to be a hot spot for the virus. https://t.co/wUxnuebCMI","id":{"$numberLong":"1238924732650655745"},"date":{"$date":{"$numberLong":"1584217649000"}},"username":"tati_vict"}
{"_id":{"$oid":"5e6d3e32d15d2c2ec652e680"},"text":"#CoronaVirus #COVIDー19 reminds me of the Everybody Loves Raymond episode where the guy sneezes on Ray Barone in the… https://t.co/JMO9hr5Igy","id":{"$numberLong":"1238924733158023168"},"date":{"$date":{"$numberLong":"1584217649000"}},"username":"seasoundreign"}
{"_id":{"$oid":"5e6d3e32d15d2c2ec652e681"},"text":"RT @themaxburns: Has anyone seen an idea they proposed move from radical to mainstream as quickly as @AndrewYang and UBI? \n\nThe #Coronaviru…","id":{"$numberLong":"1238924733292269568"},"date":{"$date":{"$numberLong":"1584217649000"}},"username":"LibertySmurf"}
{"_id":{"$oid":"5e6d3e32d15d2c2ec652e682"},"text":"RT @letat_lechat: Crucial takeaway from Trump’s disastrous #coronavirus response:\n\nRepublicans sold the dangerous lie that federal governme…","id":{"$numberLong":"1238924733376155648"},"date":{"$date":{"$numberLong":"1584217649000"}},"username":"persistentpengn"}
{"_id":{"$oid":"5e6d3e32d15d2c2ec652e683"},"text":"RT @PoliticusSarah: Trump tells Kelly O’Donnell to “just relax” when she asks him about the mixed messages he’s been sending on the #corona…","id":{"$numberLong":"1238924733414092802"},"date":{"$date":{"$numberLong":"1584217649000"}},"username":"cathy_cap2ax"}
{"_id":{"$oid":"5e6d3e32d15d2c2ec652e684"},"text":"RT @ccarolinekruer: Remember this when someone says “this shouldn’t be political.” \n\nThen tell me why 40 Republicans just voted against sav…","id":{"$numberLong":"1238924733623570432"},"date":{"$date":{"$numberLong":"1584217649000"}},"username":"7thbestpoet"}
{"_id":{"$oid":"5e6d3e32d15d2c2ec652e685"},"text":"#CoronaVirus Cardi B remix https://t.co/cc1NIa8AnK it’s gettin real!","id":{"$numberLong":"1238924733556633601"},"date":{"$date":{"$numberLong":"1584217649000"}},"username":"James_Barkley"}
{"_id":{"$oid":"5e6d3e32d15d2c2ec652e686"},"text":"@ANI What about the fake news released by the Indian Government regarding the outbreak of #coronavirus in #Delhi? 🤨","id":{"$numberLong":"1238924733833510924"},"date":{"$date":{"$numberLong":"1584217649000"}},"username":"_NadeemZaidi"}
{"_id":{"$oid":"5e6d3e32d15d2c2ec652e687"},"text":"RT @AdityaRajKaul: BIG: President of Iran Hassan Rouhani pleads before Indian PM Narendra Modi for help amidst #CoronaVirus pandemic which…","id":{"$numberLong":"1238924733824921600"},"date":{"$date":{"$numberLong":"1584217649000"}},"username":"raag124"}
{"_id":{"$oid":"5e6d3e32d15d2c2ec652e688"},"text":"RT @HanksKendyl: Soooooo.... that’s not good.","id":{"$numberLong":"1238924733913194496"},"date":{"$date":{"$numberLong":"1584217649000"}},"username":"mike_412"}
{"_id":{"$oid":"5e6d3e33d15d2c2ec652e689"},"text":"RT @ThisGrayArea: Anyone that is minimizing #coronavirus you need to stop. If you say things like “it only kills a small percentage” you sh…","id":{"$numberLong":"1238924734194225154"},"date":{"$date":{"$numberLong":"1584217649000"}},"username":"GoldDustWoman31"}
{"_id":{"$oid":"5e6d3e33d15d2c2ec652e68a"},"text":"RT @reggieaqui: Please share...so those who are still not understanding the impact of #coronavirus and are still 'living their lives' as us…","id":{"$numberLong":"1238924734206636032"},"date":{"$date":{"$numberLong":"1584217649000"}},"username":"_SmithDavid"}
{"_id":{"$oid":"5e6d3e33d15d2c2ec652e68b"},"text":"RT @steve_sps: Is there anybody out there?\nIs there anybody out there?\nIs there anybody out there?\nIs there anybody still out there?\n\n#coro…","id":{"$numberLong":"1238924734378708993"},"date":{"$date":{"$numberLong":"1584217649000"}},"username":"Dettoni_Agustin"}
{"_id":{"$oid":"5e6d3e33d15d2c2ec652e68c"},"text":"RT @NFL_Memes: BREAKING: Dallas Cowboys QB Dak Prescott has tested positive for being overrated. #Coronavirus","id":{"$numberLong":"1238924734391365632"},"date":{"$date":{"$numberLong":"1584217649000"}},"username":"EllayHeys"}
{"_id":{"$oid":"5e6d3e33d15d2c2ec652e68d"},"text":"RT @djdommb: Spread the good details just like you spread the negative ones https://t.co/MsrUxNuMpW","id":{"$numberLong":"1238924734412324865"},"date":{"$date":{"$numberLong":"1584217649000"}},"username":"settsus"}
{"_id":{"$oid":"5e6d3e33d15d2c2ec652e68e"},"text":"RT @BethRigby: Number of #coronavirus cases to 1,140 in UK (up 342 on yesterday and near double number on Thursday - 590)","id":{"$numberLong":"1238924734508736513"},"date":{"$date":{"$numberLong":"1584217649000"}},"username":"Icky_84"}
{"_id":{"$oid":"5e6d3e33d15d2c2ec652e68f"},"text":"RT @djdommb: Spread the good details just like you spread the negative ones","id":{"$numberLong":"1238924734533963778"},"date":{"$date":{"$numberLong":"1584217649000"}},"username":"numbboyy"}
